ca_pwt/__about__.py
ca_pwt/__init__.py
ca_pwt/__main__.py
ca_pwt/app.py
ca_pwt/applications.py
ca_pwt/authentication.py
ca_pwt/commands.py
ca_pwt/directory_roles.py
ca_pwt/groups.py
ca_pwt/policies.py
ca_pwt/policies_mappings.py
ca_pwt/users.py
ca_pwt/helpers/graph_api.py
ca_pwt/helpers/utils.py
ca_pwt-0.1.0.dist-info/METADATA
ca_pwt-0.1.0.dist-info/WHEEL
ca_pwt-0.1.0.dist-info/entry_points.txt
ca_pwt-0.1.0.dist-info/licenses/LICENSE
ca_pwt-0.1.0.dist-info/RECORD
