Metadata-Version: 2.1
Name: ca-pwt
Version: 0.1.0
Summary: CA-PowerToys is a set of tools to help you manage Conditional Access policies. It is a command line tool that can be used to export, import, and clean up Conditional Access policies and associated Groups
Project-URL: Documentation, https://github.com/0x6f677548/ca-pwt#readme
Project-URL: Issues, https://github.com/0x6f677548/ca-pwt/issues
Project-URL: Source, https://github.com/0x6f677548/ca-pwt
Author: 0x6f677546 (Hugo Batista)
License-Expression: MIT
License-File: LICENSE
Keywords: azure,azure-ad,conditional-access,entraid,microsoft,policies,policy-as-code
Classifier: Development Status :: 4 - Beta
Classifier: Intended Audience :: Developers
Classifier: Intended Audience :: Information Technology
Classifier: Intended Audience :: System Administrators
Classifier: License :: OSI Approved :: MIT License
Classifier: Operating System :: OS Independent
Classifier: Programming Language :: Python
Classifier: Programming Language :: Python :: 3.7
Classifier: Programming Language :: Python :: 3.8
Classifier: Programming Language :: Python :: 3.9
Classifier: Programming Language :: Python :: 3.10
Classifier: Programming Language :: Python :: 3.11
Classifier: Programming Language :: Python :: Implementation :: CPython
Classifier: Programming Language :: Python :: Implementation :: PyPy
Classifier: Topic :: Software Development
Requires-Python: >=3.7
Requires-Dist: click>=8.1.7
Requires-Dist: msal>=1.24.1
Requires-Dist: requests>=2.31.0
Requires-Dist: types-requests>=2.31.0
